unasyncd/__init__.py
unasyncd/_version.py
unasyncd/cli.py
unasyncd/config.py
unasyncd/main.py
unasyncd/transformers.py
unasyncd-0.10.0.dist-info/METADATA
unasyncd-0.10.0.dist-info/WHEEL
unasyncd-0.10.0.dist-info/entry_points.txt
unasyncd-0.10.0.dist-info/licenses/LICENSE
unasyncd-0.10.0.dist-info/RECORD
