Metadata-Version: 2.4
Name: unasyncd
Version: 0.10.0
Summary: A tool to transform asynchronous Python code to synchronous Python code.
Author-email: Janek Nouvertné <provinzkraut@posteo.de>
License-Expression: MIT
License-File: LICENSE
Requires-Python: >=3.10
Requires-Dist: anyio>=4.0.0
Requires-Dist: click>=8.1.7
Requires-Dist: importlib-metadata>=8.0.0; python_version < '3.10'
Requires-Dist: libcst<2,>=1.0.0
Requires-Dist: msgspec>=0.19
Requires-Dist: rich-click>=1.6.1
Requires-Dist: rich~=13.6.0
Requires-Dist: tomli-w>=1.0.0
Requires-Dist: tomli>=2.0.1; python_version < '3.11'
Provides-Extra: ruff
Requires-Dist: ruff; extra == 'ruff'
